git_bob/__init__.py
git_bob/_ai_github_utilities.py
git_bob/_endpoints.py
git_bob/_github_utilities.py
git_bob/_gitlab_utilities.py
git_bob/_logger.py
git_bob/_terminal.py
git_bob/_utilities.py
git_bob/data/__init__.py
git_bob/data/slide_template.pptx
git_bob-0.27.2.dist-info/licenses/LICENSE
git_bob-0.27.2.dist-info/METADATA
git_bob-0.27.2.dist-info/WHEEL
git_bob-0.27.2.dist-info/entry_points.txt
git_bob-0.27.2.dist-info/top_level.txt
git_bob-0.27.2.dist-info/RECORD
