Metadata-Version: 2.4
Name: git-bob
Version: 0.27.2
Summary: git-bob uses AI to solve Github-issues. It runs inside the Github CI, no need to install anything on your computer.
Home-page: https://github.com/haesleinhuepf/git-bob
Author: Robert Haase
Author-email: robert.haase@uni-leipzig.de
License: BSD-3-Clause
Project-URL: Bug Tracker, https://github.com/haesleinhuepf/git-bob/issues
Project-URL: Documentation, https://github.com/haesleinhuepf/git-bob#README.md
Project-URL: Source Code, https://github.com/haesleinhuepf/git-bob
Project-URL: User Support, https://github.com/haesleinhuepf/git-bob/issues
Classifier: Development Status :: 2 - Pre-Alpha
Classifier: Intended Audience :: Developers
Classifier: Operating System :: OS Independent
Classifier: Programming Language :: Python
Classifier: Programming Language :: Python :: 3
Classifier: Programming Language :: Python :: 3.9
Classifier: Programming Language :: Python :: 3.10
Classifier: Programming Language :: Python :: 3.11
Classifier: Topic :: Scientific/Engineering :: Image Processing
Requires-Python: >=3.9
License-File: LICENSE
Requires-Dist: anthropic
Requires-Dist: openai
Requires-Dist: google-generativeai
Requires-Dist: pygithub
Requires-Dist: toolz
Requires-Dist: azure-ai-inference
Requires-Dist: nbconvert
Requires-Dist: nbformat
Requires-Dist: Pillow
Requires-Dist: matplotlib
Requires-Dist: numpy
Requires-Dist: scipy
Requires-Dist: requests
Requires-Dist: ipykernel
Requires-Dist: setuptools
Requires-Dist: wheel
Requires-Dist: urllib3
Requires-Dist: requests-toolbelt
Requires-Dist: twine
Requires-Dist: python-gitlab
Requires-Dist: python-pptx
Requires-Dist: mistralai
Requires-Dist: docx2markdown
Requires-Dist: build
Provides-Extra: testing
Requires-Dist: tox; extra == "testing"
Requires-Dist: pytest; extra == "testing"
Requires-Dist: pytest-cov; extra == "testing"
Dynamic: license-file
